balloon_learning_environment/__init__.py
balloon_learning_environment/acme_utils.py
balloon_learning_environment/distributed_train_acme_qrdqn.py
balloon_learning_environment/train.py
balloon_learning_environment/train_acme_qrdqn.py
balloon_learning_environment/train_lib.py
balloon_learning_environment/train_lib_test.py
balloon_learning_environment/agents/__init__.py
balloon_learning_environment/agents/acme_eval_agent.py
balloon_learning_environment/agents/agent.py
balloon_learning_environment/agents/agent_registry.py
balloon_learning_environment/agents/agent_test.py
balloon_learning_environment/agents/dopamine_utils.py
balloon_learning_environment/agents/dopamine_utils_test.py
balloon_learning_environment/agents/dqn_agent.py
balloon_learning_environment/agents/dqn_agent_test.py
balloon_learning_environment/agents/exploration.py
balloon_learning_environment/agents/exploration_test.py
balloon_learning_environment/agents/marco_polo_exploration.py
balloon_learning_environment/agents/marco_polo_exploration_test.py
balloon_learning_environment/agents/mlp_agent.py
balloon_learning_environment/agents/mlp_agent_test.py
balloon_learning_environment/agents/networks.py
balloon_learning_environment/agents/networks_test.py
balloon_learning_environment/agents/perciatelli44.py
balloon_learning_environment/agents/perciatelli44_test.py
balloon_learning_environment/agents/quantile_agent.py
balloon_learning_environment/agents/quantile_agent_test.py
balloon_learning_environment/agents/random_walk_agent.py
balloon_learning_environment/agents/random_walk_agent_test.py
balloon_learning_environment/agents/station_seeker_agent.py
balloon_learning_environment/agents/station_seeker_agent_test.py
balloon_learning_environment/agents/configs/__init__.py
balloon_learning_environment/agents/configs/dqn.gin
balloon_learning_environment/agents/configs/finetune_perciatelli.gin
balloon_learning_environment/agents/configs/mlp.gin
balloon_learning_environment/agents/configs/quantile.gin
balloon_learning_environment-1.0.1.dist-info/LICENSE
balloon_learning_environment-1.0.1.dist-info/METADATA
balloon_learning_environment-1.0.1.dist-info/WHEEL
balloon_learning_environment-1.0.1.dist-info/entry_points.txt
balloon_learning_environment-1.0.1.dist-info/top_level.txt
balloon_learning_environment-1.0.1.dist-info/RECORD
