Metadata-Version: 2.1
Name: balloon-learning-environment
Version: 1.0.1
Summary: UNKNOWN
License: UNKNOWN
Platform: UNKNOWN
Requires-Python: >=3.7
License-File: LICENSE
Requires-Dist: absl-py
Requires-Dist: dopamine-rl (>=4.0.0)
Requires-Dist: flax
Requires-Dist: gin-config
Requires-Dist: gym
Requires-Dist: jax (>=0.2.28)
Requires-Dist: jaxlib (>=0.1.76)
Requires-Dist: opensimplex (<=0.3.0)
Requires-Dist: s2sphere
Requires-Dist: scikit-learn
Requires-Dist: tensorflow
Requires-Dist: tensorflow-probability
Requires-Dist: transitions
Provides-Extra: acme
Requires-Dist: dm-acme ; extra == 'acme'
Requires-Dist: dm-haiku ; extra == 'acme'
Requires-Dist: dm-reverb ; extra == 'acme'
Requires-Dist: dm-sonnet ; extra == 'acme'
Requires-Dist: rlax ; extra == 'acme'
Requires-Dist: xmanager ; extra == 'acme'
